mspac/__init__.py
mspac/mspac_tool.py
mspac-0.3.5.dist-info/DESCRIPTION.rst
mspac-0.3.5.dist-info/METADATA
mspac-0.3.5.dist-info/RECORD
mspac-0.3.5.dist-info/WHEEL
mspac-0.3.5.dist-info/entry_points.txt
mspac-0.3.5.dist-info/metadata.json
mspac-0.3.5.dist-info/top_level.txt
