Metadata-Version: 2.0
Name: mspac
Version: 0.3.5
Summary: An apt-like pacman wrapper.
Home-page: https://github.com/baltasarq/mspac/
Author: dev::baltasarq
Author-email: baltasarq@gmail.com
License: MIT
Keywords: pacman aur
Platform: arch linux
Classifier: Development Status :: 5 - Production/Stable
Classifier: Intended Audience :: End Users/Desktop
Classifier: Topic :: System :: Installation/Setup
Classifier: Operating System :: POSIX :: Linux
Classifier: License :: OSI Approved :: MIT License
Classifier: Programming Language :: Python :: 3
